{"body": "\n\n\n\nJob requirements: \r\nUniversity degree, preferably in Economics;\r\nEnglish knowledge both spoken and written; Banking experience is needed; \r\nCustomer-care oriented, with good communication skills, able to solve promptly and professionally the customers' requests;\r\nGood selling and negotiation skills also requested;\r\nDynamic and flexible person, enthusiastic, with initiative and a pro-active attitude;\r\nQualification as bank assurance agent would be a plus. \n\r\nKey responsibilities:\r\n The nominees will interact directly with customers, open and administrate their accounts and ensure information on the bank's products and services; she/ he will promote products and services to clients, analyse and manage applications for card issuance. All applications will be treated in strictest confidence. Only short-listed candidates will be contacted for an interview.\n \n\n\n", "title": "CONSILIER CLIENTI - FRONT OFFICE - UNITATE BANCARA", "company_url": "http://www.bestjobs.ro/firme/alpha-bank-romania/678/1", "career_level": "Entry, Middle", "company": "ALPHA BANK ROMANIA", "locations": "\nBuzău, Județul Buzău, România;Alba Iulia, Județul Alba, România;Bârlad, Județul Vaslui, România;Bistrița, Județul Bistrița-Năsăud, România;București, Municipiul București, România;Cluj-Napoca, Județul Cluj, România;Constanța, Județul Constanța, România;Iași, Județul Iași, România;Odorheiu Secuiesc, Județul Harghita, România;Oradea, Județul Bihor, România;Piatra Neamț, Județul Neamț, România;Sibiu, Județul Sibiu, România;Timișoara, Județul Timiș, România\n", "url": "http://www.bestjobs.ro/locuri-de-munca-consilier-clienti-front-office-unitate-bancara/749405/1"}